setup.py
hashTag/DBConnectionHandler.py
hashTag/DBConnectiontests.py
hashTag/DataFetchEngine.py
hashTag/Datastore.py
hashTag/HashTag.py
hashTag/Parser.py
hashTag/QueryDispatch.py
hashTag/TagSearch.py
hashTag/__init__.py
hashTag/dbInitlizer.py
hashTag/sample_test.py
hashtag.egg-info/PKG-INFO
hashtag.egg-info/SOURCES.txt
hashtag.egg-info/dependency_links.txt
hashtag.egg-info/not-zip-safe
hashtag.egg-info/top_level.txt