Metadata-Version: 1.0
Name: hashtag
Version: 0.1
Summary: hashtagging for immortals.
Home-page: http://github.com/adivandhya/hashTag
Author: Adivandhya | Rahul | Sameer
Author-email: adivandhya@yahoo.co.in
License: MIT
Platform: UNKNOWN
